MANIFEST.in
README.txt
setup.cfg
setup.py
yxspkg_encrypt.py
yxspkg_encrypt.egg-info/PKG-INFO
yxspkg_encrypt.egg-info/SOURCES.txt
yxspkg_encrypt.egg-info/dependency_links.txt
yxspkg_encrypt.egg-info/entry_points.txt
yxspkg_encrypt.egg-info/requires.txt
yxspkg_encrypt.egg-info/top_level.txt