Metadata-Version: 1.1
Name: yxspkg-encrypt
Version: 1.2.3
Summary: A simple API to encrypt data. Encrypt algorithm is based on linear congruence
Home-page: https://github.com/blacksong
Author: Blacksong
Author-email: blacksong@yeah.net
License: UNKNOWN
Platform: any
Classifier: Programming Language :: Python :: 3
Classifier: Operating System :: OS Independent
Classifier: Topic :: Software Development :: Libraries :: Python Modules
